odoo9_addon_mis_builder-9.0.3.5.0-nspkg.pth
odoo_addons/mis_builder/README.rst
odoo_addons/mis_builder/__init__.py
odoo_addons/mis_builder/__openerp__.py
odoo_addons/mis_builder/datas/ir_cron.xml
odoo_addons/mis_builder/i18n/ca.po
odoo_addons/mis_builder/i18n/de.po
odoo_addons/mis_builder/i18n/el.po
odoo_addons/mis_builder/i18n/el_GR.po
odoo_addons/mis_builder/i18n/es.po
odoo_addons/mis_builder/i18n/fr.po
odoo_addons/mis_builder/i18n/hr.po
odoo_addons/mis_builder/i18n/mis_builder.pot
odoo_addons/mis_builder/i18n/nl.po
odoo_addons/mis_builder/i18n/nl_NL.po
odoo_addons/mis_builder/i18n/pt.po
odoo_addons/mis_builder/i18n/pt_BR.po
odoo_addons/mis_builder/migrations/8.0.2.0.0/post-migration.py
odoo_addons/mis_builder/migrations/8.0.2.0.0/pre-migration.py
odoo_addons/mis_builder/models/__init__.py
odoo_addons/mis_builder/models/accounting_none.py
odoo_addons/mis_builder/models/aep.py
odoo_addons/mis_builder/models/aggregate.py
odoo_addons/mis_builder/models/data_error.py
odoo_addons/mis_builder/models/kpimatrix.py
odoo_addons/mis_builder/models/mis_kpi_data.py
odoo_addons/mis_builder/models/mis_report.py
odoo_addons/mis_builder/models/mis_report_instance.py
odoo_addons/mis_builder/models/mis_report_style.py
odoo_addons/mis_builder/models/mis_safe_eval.py
odoo_addons/mis_builder/models/simple_array.py
odoo_addons/mis_builder/readme/CONTRIBUTORS.rst
odoo_addons/mis_builder/readme/DESCRIPTION.rst
odoo_addons/mis_builder/readme/DEVELOP.rst
odoo_addons/mis_builder/readme/HISTORY.rst
odoo_addons/mis_builder/readme/INSTALL.rst
odoo_addons/mis_builder/readme/ROADMAP.rst
odoo_addons/mis_builder/readme/USAGE.rst
odoo_addons/mis_builder/readme/newsfragments/.gitignore
odoo_addons/mis_builder/report/__init__.py
odoo_addons/mis_builder/report/mis_report_instance_qweb.py
odoo_addons/mis_builder/report/mis_report_instance_qweb.xml
odoo_addons/mis_builder/report/mis_report_instance_xlsx.py
odoo_addons/mis_builder/report/mis_report_instance_xlsx.xml
odoo9_addon_mis_builder-9.0.3.5.0.dist-info/METADATA
odoo9_addon_mis_builder-9.0.3.5.0.dist-info/WHEEL
odoo9_addon_mis_builder-9.0.3.5.0.dist-info/namespace_packages.txt
odoo9_addon_mis_builder-9.0.3.5.0.dist-info/top_level.txt
odoo9_addon_mis_builder-9.0.3.5.0.dist-info/RECORD
